README.rst
setup.cfg
setup.py
dialogue_opentok.egg-info/PKG-INFO
dialogue_opentok.egg-info/SOURCES.txt
dialogue_opentok.egg-info/dependency_links.txt
dialogue_opentok.egg-info/requires.txt
dialogue_opentok.egg-info/top_level.txt
opentok/__init__.py
opentok/archives.py
opentok/broadcast.py
opentok/endpoints.py
opentok/exceptions.py
opentok/opentok.py
opentok/session.py
opentok/sip_call.py
opentok/stream.py
opentok/streamlist.py
opentok/version.py