Metadata-Version: 1.1
Name: dialogue-opentok
Version: 2.10.0
Summary: OpenTok server-side SDK
Home-page: https://github.com/opentok/Opentok-Python-SDK
Author: TokBox, Inc.
Author-email: support@tokbox.com
License: LICENSE.txt
Keywords: video chat tokbox tok opentok python media webrtc archiving realtime
Platform: UNKNOWN
Classifier: Development Status :: 5 - Production/Stable
Classifier: Intended Audience :: Developers
Classifier: Intended Audience :: Telecommunications Industry
Classifier: License :: OSI Approved :: MIT License
Classifier: Programming Language :: Python :: 2
Classifier: Programming Language :: Python :: 2.6
Classifier: Programming Language :: Python :: 2.7
Classifier: Programming Language :: Python :: 3
Classifier: Programming Language :: Python :: 3.3
Classifier: Programming Language :: Python :: 3.4
Classifier: Programming Language :: Python :: 3.5
Classifier: Programming Language :: Python :: 3.6
Classifier: Topic :: Communications
Classifier: Topic :: Communications :: Chat
Classifier: Topic :: Communications :: Conferencing
Classifier: Topic :: Multimedia :: Video :: Capture
Classifier: Topic :: Multimedia :: Video :: Display
Classifier: Topic :: Multimedia :: Sound/Audio :: Players
Classifier: Topic :: Multimedia :: Sound/Audio :: Capture/Recording
Classifier: Topic :: Software Development :: Libraries :: Python Modules
